README.txt
setup.py
collective/__init__.py
collective.skinny.egg-info/PKG-INFO
collective.skinny.egg-info/SOURCES.txt
collective.skinny.egg-info/dependency_links.txt
collective.skinny.egg-info/entry_points.txt
collective.skinny.egg-info/namespace_packages.txt
collective.skinny.egg-info/not-zip-safe
collective.skinny.egg-info/requires.txt
collective.skinny.egg-info/top_level.txt
collective/skinny/__init__.py
collective/skinny/base.py
collective/skinny/configure.zcml
collective/skinny/content.py
collective/skinny/debug.py
collective/skinny/fourohfour.py
collective/skinny/interfaces.py
collective/skinny/main.py
collective/skinny/patch.py
collective/skinny/resources/favicon.ico
collective/skinny/resources/logo.png
collective/skinny/resources/styles.css
collective/skinny/templates/404.pt
collective/skinny/templates/head.pt
collective/skinny/templates/main.pt
collective/skinny/templates/content/document.pt
docs/HISTORY.txt
docs/THANKS.txt