Metadata-Version: 1.0
Name: collective.skinny
Version: 0.6
Summary: Plone theming for mortals: A simple example to get you started quickly with your own public skin
Home-page: http://pypi.python.org/pypi/collective.skinny
Author: Daniel Nouri
Author-email: daniel.nouri@gmail.com
License: LGPL
Keywords: plone zope public skin template theming
Platform: UNKNOWN
Classifier: Programming Language :: Python
Classifier: Topic :: Software Development :: Libraries :: Python Modules
Classifier: Intended Audience :: Developers
Classifier: Framework :: Plone
Classifier: Framework :: Zope2
